pyaket/Cargo.lock
pyaket/Cargo.toml
pyaket/__init__.py
pyaket/__main__.py
pyaket/build.rs
pyaket/project.py
pyaket/targets.py
pyaket/.cargo/config.toml
pyaket/pyaket/assets.rs
pyaket/pyaket/envy.rs
pyaket/pyaket/lib.rs
pyaket/pyaket/logging.rs
pyaket/pyaket/main.rs
pyaket/pyaket/project.rs
pyaket/pyaket/runtime.rs
pyaket/pyaket/subproc.rs
pyaket/pyaket/commands/mod.rs
pyaket/pyaket/commands/manager/mod.rs
pyaket/pyaket/commands/manager/uv.rs
pyaket/pyaket/commands/manager/version.rs
pyaket/resources/targets.json
pyaket-0.10.0.dist-info/METADATA
pyaket-0.10.0.dist-info/WHEEL
pyaket-0.10.0.dist-info/entry_points.txt
pyaket-0.10.0.dist-info/RECORD
