Metadata-Version: 2.4
Name: pyaket
Version: 0.10.0
Summary: 📦 Easy Python to Fast Executables
Project-URL: GitHub, https://github.com/BrokenSource/Pyaket
Project-URL: Changelog, https://pyaket.dev/about/changelog
Project-URL: Contact, https://pyaket.dev/about/contact
Project-URL: Docs, https://pyaket.dev/docs
Project-URL: Homepage, https://pyaket.dev
Author: Tremeschin
License-Expression: AGPL-3.0
Requires-Python: >=3.10
Requires-Dist: attrs~=25.0
Requires-Dist: dotmap~=1.3
Requires-Dist: pillow~=12.0
Requires-Dist: pydantic~=2.12
Requires-Dist: rich~=14.2
Requires-Dist: rustbin~=1.28
Requires-Dist: structlog~=25.5
Requires-Dist: typer~=0.21
Provides-Extra: all
Requires-Dist: cargo-zigbuild; extra == 'all'
Requires-Dist: ziglang; extra == 'all'
Provides-Extra: xwin
Requires-Dist: cargo-xwin; extra == 'xwin'
Requires-Dist: ninja; extra == 'xwin'
Provides-Extra: zig
Requires-Dist: cargo-zigbuild; extra == 'zig'
Requires-Dist: ziglang; extra == 'zig'
